Metadata-Version: 2.4
Name: llamea
Version: 1.1.10
Summary: LLaMEA is a Python framework for automatically generating and refining metaheuristic optimization algorithms using large language models, featuring optional in-the-loop hyper-parameter optimization.
Project-URL: Homepage, https://github.com/XAI-liacs/LLaMEA
Project-URL: Repository, https://github.com/XAI-liacs/LLaMEA
Author-email: Niki van Stein <n.van.stein@liacs.leidenuniv.nl>
License-Expression: MIT
License-File: LICENSE
Requires-Python: <4,>=3.11
Requires-Dist: configspace<2,>=1.2.0
Requires-Dist: google-generativeai<0.9,>=0.8.1
Requires-Dist: joblib<2,>=1.4.2
Requires-Dist: jsonlines<5,>=4.0.0
Requires-Dist: numpy<3,>=1
Requires-Dist: ollama<1,>=0.5.3
Requires-Dist: openai<2,>=1.99.1
Requires-Dist: tqdm<5,>=4.66.4
